django_drf_keycloak_auth/__init__.py
django_drf_keycloak_auth/authentication.py
django_drf_keycloak_auth/keycloak_utils.py
django_drf_keycloak_auth/schema.py
django_drf_keycloak_auth/serializers.py
django_drf_keycloak_auth/urls.py
django_drf_keycloak_auth/version.py
django_drf_keycloak_auth/views.py
django_drf_keycloak_auth/models/__init__.py
django_drf_keycloak_auth/models/user.py
django_drf_keycloak_auth-0.1.0.dist-info/LICENSE
django_drf_keycloak_auth-0.1.0.dist-info/METADATA
django_drf_keycloak_auth-0.1.0.dist-info/WHEEL
django_drf_keycloak_auth-0.1.0.dist-info/top_level.txt
django_drf_keycloak_auth-0.1.0.dist-info/RECORD
