Metadata-Version: 2.1
Name: django-drf-keycloak-auth
Version: 0.1.0
Summary: Django app for Keycloak OAuth2 authentication with DRF.
Home-page: https://github.com/xiaobitipao/django-drf-keycloak-auth
Author: xiaobitipao
Author-email: xiaobitipao@gmail.com
License: MIT
Keywords: keycloak,django,djangorestframework,oauth2
Classifier: Framework :: Django
Classifier: Development Status :: 5 - Production/Stable
Classifier: Programming Language :: Python
Classifier: Programming Language :: Python :: 3
Classifier: Programming Language :: Python :: 3.10
Classifier: Programming Language :: Python :: 3.11
Classifier: Programming Language :: Python :: 3.12
Classifier: Programming Language :: Python :: 3.13
Classifier: Programming Language :: Python :: Implementation :: PyPy
Classifier: Intended Audience :: Developers
Classifier: License :: OSI Approved :: MIT License
Classifier: Operating System :: OS Independent
Requires-Python: >=3.11
License-File: LICENSE
Requires-Dist: python-dotenv>=1.1.1
Requires-Dist: Django>=5.2.7
Requires-Dist: djangorestframework>=3.16.1
Requires-Dist: python-keycloak>=5.8.1
Requires-Dist: pydantic>=2.12.1
Requires-Dist: pydantic-settings>=2.11.0
